vip_hci/__init__.py
vip_hci/vip_ds9.py
vip_hci/config/__init__.py
vip_hci/config/mem.py
vip_hci/config/param.py
vip_hci/config/paramenum.py
vip_hci/config/timing.py
vip_hci/config/utils_conf.py
vip_hci/config/utils_param.py
vip_hci/fits/__init__.py
vip_hci/fits/fits.py
vip_hci/fits/headers.py
vip_hci/fm/__init__.py
vip_hci/fm/fakecomp.py
vip_hci/fm/fakedisk.py
vip_hci/fm/negfc_fmerit.py
vip_hci/fm/negfc_mcmc.py
vip_hci/fm/negfc_nested.py
vip_hci/fm/negfc_simplex.py
vip_hci/fm/negfc_speckle_noise.py
vip_hci/fm/negfd_fmerit.py
vip_hci/fm/negfd_interp.py
vip_hci/fm/negfd_simplex.py
vip_hci/fm/scattered_light_disk.py
vip_hci/fm/utils_mcmc.py
vip_hci/fm/utils_negfc.py
vip_hci/fm/utils_negfd.py
vip_hci/greedy/__init__.py
vip_hci/greedy/inmf_fullfr.py
vip_hci/greedy/ipca_fullfr.py
vip_hci/greedy/irollsub.py
vip_hci/invprob/__init__.py
vip_hci/invprob/andromeda.py
vip_hci/invprob/fmmf.py
vip_hci/invprob/paco.py
vip_hci/invprob/utils_andro.py
vip_hci/metrics/__init__.py
vip_hci/metrics/completeness.py
vip_hci/metrics/contrcurve.py
vip_hci/metrics/detection.py
vip_hci/metrics/roc.py
vip_hci/metrics/snr_source.py
vip_hci/metrics/stim.py
vip_hci/objects/__init__.py
vip_hci/objects/dataset.py
vip_hci/objects/postproc.py
vip_hci/objects/ppandromeda.py
vip_hci/objects/ppfmmf.py
vip_hci/objects/ppframediff.py
vip_hci/objects/ppllsg.py
vip_hci/objects/pploci.py
vip_hci/objects/ppmediansub.py
vip_hci/objects/ppnmf.py
vip_hci/objects/pppca.py
vip_hci/preproc/__init__.py
vip_hci/preproc/badframes.py
vip_hci/preproc/badpixremoval.py
vip_hci/preproc/cosmetics.py
vip_hci/preproc/derotation.py
vip_hci/preproc/parangles.py
vip_hci/preproc/recentering.py
vip_hci/preproc/rescaling.py
vip_hci/preproc/skysubtraction.py
vip_hci/preproc/subsampling.py
vip_hci/psfsub/__init__.py
vip_hci/psfsub/framediff.py
vip_hci/psfsub/llsg.py
vip_hci/psfsub/loci.py
vip_hci/psfsub/medsub.py
vip_hci/psfsub/nmf_fullfr.py
vip_hci/psfsub/nmf_local.py
vip_hci/psfsub/pca_fullfr.py
vip_hci/psfsub/pca_local.py
vip_hci-2.0.0.dist-info/licenses/LICENSE
vip_hci-2.0.0.dist-info/METADATA
vip_hci-2.0.0.dist-info/WHEEL
vip_hci-2.0.0.dist-info/top_level.txt
vip_hci-2.0.0.dist-info/RECORD
