Metadata-Version: 2.4
Name: vip_hci
Version: 2.0.0
Summary: Package for astronomical high-contrast image processing.
Author: Carlos Alberto Gomez Gonzalez
Author-email: Valentin Christiaens <valentin.christiaens@uliege.be>
License-Expression: MIT
Project-URL: Homepage, https://github.com/vortex-exoplanet/VIP
Classifier: Intended Audience :: Science/Research
Classifier: Natural Language :: English
Classifier: Operating System :: MacOS :: MacOS X
Classifier: Operating System :: POSIX :: Linux
Classifier: Programming Language :: Python :: 3 :: Only
Classifier: Programming Language :: Python :: 3.10
Classifier: Programming Language :: Python :: 3.11
Classifier: Programming Language :: Python :: 3.12
Classifier: Programming Language :: Python :: 3.13
Classifier: Topic :: Scientific/Engineering :: Astronomy
Requires-Python: >=3.10
License-File: LICENSE
Requires-Dist: astropy>=5.0.0
Requires-Dist: corner>=2.2.1
Requires-Dist: dataclass_builder>=1.2.0
Requires-Dist: emcee>=3.1.0
Requires-Dist: hciplot>=0.2.4
Requires-Dist: matplotlib>=3.7.0
Requires-Dist: nestle>=0.2.0
Requires-Dist: numpy>=1.21.2
Requires-Dist: pandas>=1.3.3
Requires-Dist: photutils>=1.2.0
Requires-Dist: psutil>=5.9.0
Requires-Dist: pyprind>=2.11.3
Requires-Dist: scipy>=1.7.2
Requires-Dist: scikit-image>=0.19.0
Requires-Dist: scikit-learn>=1.0.2
Dynamic: license-file
